{
  "name": "SparseBox",
  "identifier": "com.kdt.sparsebox",
  "bundleIdentifier": "com.kdt.sparsebox",
  "developerName": "khanhduytran0",
  "version": "6",
  "versionDate": "2024-12-13T16:05:34Z",
  "versionDescription": "On-device backup restoration? rewrote SparseRestore to swift",
  "subtitle": "SparseBox App",
  "downloadURL": "https://files.catbox.moe/0iquw0.ipa",
  "apps": [
    {
      "versions": [
        {
          "version": "11",
          "date": "2024-12-13T16:36:33Z",
          "localizedDescription": "On-device backup restoration? rewrote SparseRestore to swift",
          "downloadURL": "https://files.catbox.moe/0iquw0.ipa",
          "size": "7278761"
        }
      ]
    }
  ]
}
